fishscale/__init__.py
fishscale/__version__.py
fishscale/combine.py
fishscale/move_non.py
fishscale/remove_non.py
fishscale/reverse.py
fishscale/split.py
fishscale-0.2.1.dist-info/LICENSE
fishscale-0.2.1.dist-info/METADATA
fishscale-0.2.1.dist-info/WHEEL
fishscale-0.2.1.dist-info/entry_points.txt
fishscale-0.2.1.dist-info/top_level.txt
fishscale-0.2.1.dist-info/RECORD
